{
  "Servers": {
    "1": {
      "Name": "TC Agro - PostgreSQL",
      "Group": "TC Agro Solutions",
      "Host": "postgres",
      "Port": 5432,
      "MaintenanceDB": "postgres",
      "Username": "postgres",
      "Password": "postgres",
      "SSLMode": "prefer",
      "Databases": {
        "tc-agro-identity-db": {},
        "tc-agro-farm-db": {},
        "tc-agro-sensor-ingest-db": {},
        "tc-agro-analytics-db": {}
      },
      "Comment": "PostgreSQL server with isolated databases per microservice"
    }
  }
}
